pysimplemask/__init__.py
pysimplemask/area_mask.py
pysimplemask/cli.py
pysimplemask/file_handler.py
pysimplemask/find_center.py
pysimplemask/outlier_removal.py
pysimplemask/pyqtgraph_mod.py
pysimplemask/qmap.py
pysimplemask/simplemask_kernel.py
pysimplemask/simplemask_main.py
pysimplemask/simplemask_ui.py
pysimplemask/table_model.py
pysimplemask/utils.py
pysimplemask/reader/__init__.py
pysimplemask/reader/base_reader.py
pysimplemask/reader/timepix_reader.py
pysimplemask/reader/utils.py
pysimplemask/reader/APS_8IDI/__init__.py
pysimplemask/reader/APS_8IDI/aps_8idi_reader.py
pysimplemask/reader/APS_8IDI/hdf_handler.py
pysimplemask/reader/APS_8IDI/imm_handler.py
pysimplemask/reader/APS_8IDI/rigaku_3M_handler.py
pysimplemask/reader/APS_8IDI/rigaku_handler.py
pysimplemask/reader/APS_8IDI/rigaku_six_handler.py
pysimplemask/reader/APS_8IDI/test_rigaku3m.py
pysimplemask/reader/APS_8IDI/xpcs_dataset.py
pysimplemask/reader/APS_9IDD/aps_9idd_reader.py
pysimplemask/reader/esrf_id02/esrf_hdf_handler.py
pysimplemask/resources/logo.svg
pysimplemask/ui/mask.ui
pysimplemask-0.3.1.dist-info/licenses/LICENSE
pysimplemask-0.3.1.dist-info/METADATA
pysimplemask-0.3.1.dist-info/WHEEL
pysimplemask-0.3.1.dist-info/entry_points.txt
pysimplemask-0.3.1.dist-info/top_level.txt
pysimplemask-0.3.1.dist-info/RECORD
