Metadata-Version: 2.4
Name: pysimplemask
Version: 0.3.1
Summary: A GUI for creating mask and q-partition maps for scattering patterns in preparation for SAXS/WAXS/XPCS data reduction
Author-email: Miaoqi Chu <mqichu@anl.gov>
Maintainer-email: Miaoqi Chu <mqichu@anl.gov>
License: Copyright (c) 2026, UChicago Argonne, LLC. All rights reserved.
Project-URL: bugs, https://github.com/AdvancedPhotonSource/pySimpleMask/issues
Project-URL: changelog, https://github.com/AdvancedPhotonSource/pySimpleMask/blob/master/changelog.md
Project-URL: homepage, https://github.com/AdvancedPhotonSource/pySimpleMask
Classifier: Development Status :: 4 - Beta
Classifier: Intended Audience :: Science/Research
Classifier: License :: OSI Approved :: BSD License
Classifier: Programming Language :: Python :: 3
Classifier: Programming Language :: Python :: 3.12
Classifier: Topic :: Scientific/Engineering :: Visualization
Classifier: Operating System :: OS Independent
License-File: LICENSE
Requires-Dist: numpy
Requires-Dist: scipy
Requires-Dist: h5py
Requires-Dist: hdf5plugin
Requires-Dist: scikit-image
Requires-Dist: matplotlib
Requires-Dist: pyqtgraph
Requires-Dist: PySide6==6.8.3
Requires-Dist: astropy
Requires-Dist: imagecodecs
Requires-Dist: tifffile
Provides-Extra: dev
Requires-Dist: coverage; extra == "dev"
Requires-Dist: mypy; extra == "dev"
Requires-Dist: pytest; extra == "dev"
Requires-Dist: ruff; extra == "dev"
Dynamic: license-file
